banner_minju210/__init__.py
banner_minju210/banner.py
banner_minju210-0.5.1.dist-info/METADATA
banner_minju210-0.5.1.dist-info/WHEEL
banner_minju210-0.5.1.dist-info/entry_points.txt
banner_minju210-0.5.1.dist-info/top_level.txt
banner_minju210-0.5.1.dist-info/RECORD
