Metadata-Version: 2.1
Name: banner_minju210
Version: 0.5.1
Summary: Banner Output Program
Author-email: minju210 <juliana6190210@gmail.com>
License: MIT
Project-URL: Homepage, https://github.com/minju210/banner_minju210
Project-URL: Issues, https://github.com/minju210/banner_minju210/issues
Requires-Python: >=3.9
Requires-Dist: pyfiglet >=1.0.2
